flake8_meiqia/__init__.py
flake8_meiqia/core.py
flake8_meiqia/checks/__init__.py
flake8_meiqia/checks/code.py
flake8_meiqia/checks/comments.py
flake8_meiqia/checks/excepts.py
flake8_meiqia/checks/other.py
flake8_meiqia/checks/python23.py
flake8_meiqia-0.2.0.dist-info/DESCRIPTION.rst
flake8_meiqia-0.2.0.dist-info/METADATA
flake8_meiqia-0.2.0.dist-info/RECORD
flake8_meiqia-0.2.0.dist-info/WHEEL
flake8_meiqia-0.2.0.dist-info/entry_points.txt
flake8_meiqia-0.2.0.dist-info/metadata.json
flake8_meiqia-0.2.0.dist-info/top_level.txt
