Metadata-Version: 2.0
Name: flake8-meiqia
Version: 0.2.0
Summary: Python style guideline in Meiqia
Home-page: https://github.com/Meiqia/flake8-meiqia
Author: Meiqia Developers
Author-email: dev@meiqia.com
License: Apache License 2.0
Platform: UNKNOWN
Classifier: Development Status :: 4 - Beta
Classifier: Environment :: Console
Classifier: Framework :: Flake8
Classifier: Intended Audience :: Developers
Classifier: Intended Audience :: Information Technology
Classifier: License :: OSI Approved :: Apache Software License
Classifier: Operating System :: OS Independent
Classifier: Programming Language :: Python
Classifier: Programming Language :: Python :: 2
Classifier: Programming Language :: Python :: 2.6
Classifier: Programming Language :: Python :: 2.7
Classifier: Programming Language :: Python :: 3
Classifier: Programming Language :: Python :: 3.3
Classifier: Programming Language :: Python :: 3.4
Classifier: Topic :: Software Development :: Quality Assurance
Requires-Dist: flake8
